biit/App.py
biit/ConfigManager.py
biit/ErrorManager.py
biit/Input.py
biit/UpdateManager.py
biit/__init__.py
biit/app.css
biit/invoke_in_main.py
biit/Core/Common.py
biit/Core/EvaluationEngine.py
biit/Core/FunctionLibrary.py
biit/Core/GraphBase.py
biit/Core/GraphManager.py
biit/Core/Interfaces.py
biit/Core/NodeBase.py
biit/Core/OmeroService.py
biit/Core/PathsRegistry.py
biit/Core/PinBase.py
biit/Core/PyCodeCompiler.py
biit/Core/Variable.py
biit/Core/Worker.py
biit/Core/__init__.py
biit/Core/structs.py
biit/Core/version.py
biit/Packages/__init__.py
biit/Packages/PyFlowBase/__init__.py
biit/Packages/PyFlowBase/Exporters/PythonScriptExporter.py
biit/Packages/PyFlowBase/Exporters/__init__.py
biit/Packages/PyFlowBase/Factories/PinInputWidgetFactory.py
biit/Packages/PyFlowBase/Factories/UINodeFactory.py
biit/Packages/PyFlowBase/Factories/UIPinFactory.py
biit/Packages/PyFlowBase/Factories/__init__.py
biit/Packages/PyFlowBase/FunctionLibraries/ArrayLib.py
biit/Packages/PyFlowBase/FunctionLibraries/BiitArrayNode.py
biit/Packages/PyFlowBase/FunctionLibraries/BiitLib.py
biit/Packages/PyFlowBase/FunctionLibraries/BiitNode.py
biit/Packages/PyFlowBase/FunctionLibraries/BiitNodeBase.py
biit/Packages/PyFlowBase/FunctionLibraries/BiitSimpleITKNodes.py
biit/Packages/PyFlowBase/FunctionLibraries/BiitToolNode.py
biit/Packages/PyFlowBase/FunctionLibraries/BiitUtils.py
biit/Packages/PyFlowBase/FunctionLibraries/BoolLib.py
biit/Packages/PyFlowBase/FunctionLibraries/DefaultLib.py
biit/Packages/PyFlowBase/FunctionLibraries/FloatLib.py
biit/Packages/PyFlowBase/FunctionLibraries/IOLib.py
biit/Packages/PyFlowBase/FunctionLibraries/IntLib.py
biit/Packages/PyFlowBase/FunctionLibraries/MathAbstractLib.py
biit/Packages/PyFlowBase/FunctionLibraries/MathLib.py
biit/Packages/PyFlowBase/FunctionLibraries/OmeroLib.py
biit/Packages/PyFlowBase/FunctionLibraries/PandasLib.py
biit/Packages/PyFlowBase/FunctionLibraries/PathLib.py
biit/Packages/PyFlowBase/FunctionLibraries/RandomLib.py
bioimageit-0.3.3.dist-info/LICENSE
bioimageit-0.3.3.dist-info/METADATA
bioimageit-0.3.3.dist-info/WHEEL
bioimageit-0.3.3.dist-info/top_level.txt
bioimageit-0.3.3.dist-info/RECORD
