Metadata-Version: 2.1
Name: bioimageit
Version: 0.3.3
Summary: A FAIR data management and image analysis framework
Author-email: Arthur Masson <arthur.masson@inria.fr>
License: Copyright (c) 2020, BioImageIT
Requires-Python: ==3.10.8
License-File: LICENSE
Requires-Dist: omero-py ==5.15.0
Requires-Dist: simpleitk <2.4,>=2.3.1
Requires-Dist: qtpy <3,>=2.4.1
Requires-Dist: blinker <2,>=1.8.2
Requires-Dist: keyring <26,>=25.2.1
Requires-Dist: numpy <3,>=2.0.1
Requires-Dist: pandas <3,>=2.2.2
Requires-Dist: pillow <11,>=10.4.0
Requires-Dist: pyside6 <7,>=6.7.2
Requires-Dist: pyside6-qtads <5,>=4.3.0.2
Requires-Dist: munch <5,>=4.0.0
Requires-Dist: send2trash <2,>=1.8.3
Requires-Dist: mailjet-rest <2,>=1.3.4
Provides-Extra: install
Requires-Dist: pyinstaller ; extra == 'install'
